{"P3": {"labels": ["\u8f6c\u8f7d"], "postTitle": "\u77e5\u6587\uff1a\u4e3a\u4ec0\u4e48\u6211\u89c9\u5f97\u7f8e\u56fd\u8fd8\u8981\u7e41\u8363\u51e0\u767e\u5e74", "postUrl": "post/zhi-wen-%EF%BC%9A-wei-shen-me-wo-jue-de-mei-guo-huan-yao-fan-rong-ji-bai-nian.html", "createdDate": "2024-10-13", "dateLabelColor": "#bc4c00"}, "P2": {"labels": ["documentation"], "postTitle": "1", "postUrl": "post/1.html", "createdDate": "2024-10-13", "dateLabelColor": "#bc4c00"}, "P1": {"labels": ["documentation"], "postTitle": "\u8c22\u987f", "postUrl": "post/xie-dun.html", "createdDate": "2024-10-12", "dateLabelColor": "#bc4c00"}, "labelColorDict": {"bug": "#d73a4a", "documentation": "#0075ca", "duplicate": "#cfd3d7", "enhancement": "#a2eeef", "good first issue": "#7057ff", "help wanted": "#008672", "invalid": "#e4e669", "question": "#d876e3", "wontfix": "#ffffff", "\u8f6c\u8f7d": "#0052cc"}}